justniffer/__init__.py
justniffer/class_utils.py
justniffer/cli.py
justniffer/commands.py
justniffer/config.py
justniffer/dns_info.py
justniffer/extractors.py
justniffer/formatters.py
justniffer/handlers.py
justniffer/http_info.py
justniffer/logging.py
justniffer/model.py
justniffer/settings.py
justniffer/ssh_info.py
justniffer/tls_info.py
justniffer_cli-0.2.7.dist-info/METADATA
justniffer_cli-0.2.7.dist-info/WHEEL
justniffer_cli-0.2.7.dist-info/entry_points.txt
justniffer_cli-0.2.7.dist-info/RECORD
