Metadata-Version: 2.3
Name: justniffer-cli
Version: 0.2.7
Summary: A Python-based command-line interface (CLI) for interacting with [justniffer] (https://github.com/onotelli/justniffer).
Author: Oreste Notelli
Author-email: oreste.notelli@plecno.com
Requires-Python: >=3.10,<4.0
Classifier: Environment :: Console
Classifier: Intended Audience :: System Administrators
Classifier: Operating System :: POSIX :: Linux
Classifier: Programming Language :: Python :: 3
Classifier: Programming Language :: Python :: 3.10
Classifier: Programming Language :: Python :: 3.11
Classifier: Programming Language :: Python :: 3.12
Classifier: Programming Language :: Python :: 3.13
Classifier: Topic :: Internet :: Log Analysis
Classifier: Topic :: System :: Logging
Classifier: Topic :: System :: Networking
Classifier: Topic :: System :: Networking :: Monitoring
Classifier: Topic :: Utilities
Requires-Dist: dynaconf (>=3.2.11,<4.0.0)
Requires-Dist: httptools (>=0.6.4,<0.7.0)
Requires-Dist: loguru (>=0.7.3,<0.8.0)
Requires-Dist: packaging (>=25.0,<26.0)
Requires-Dist: pydantic (>=2.11.4,<3.0.0)
Requires-Dist: pyyaml (>=6.0.2,<7.0.0)
Requires-Dist: scapy (>=2.6.1,<3.0.0)
Requires-Dist: typer (>=0.15.1,<0.16.0)
